CHANGES.txt
README.txt
bootstrap.py
buildout.cfg
setup.py
src/zope/__init__.py
src/zope.app.interpreter.egg-info/PKG-INFO
src/zope.app.interpreter.egg-info/SOURCES.txt
src/zope.app.interpreter.egg-info/dependency_links.txt
src/zope.app.interpreter.egg-info/namespace_packages.txt
src/zope.app.interpreter.egg-info/not-zip-safe
src/zope.app.interpreter.egg-info/requires.txt
src/zope.app.interpreter.egg-info/top_level.txt
src/zope/app/__init__.py
src/zope/app/interpreter/SETUP.cfg
src/zope/app/interpreter/__init__.py
src/zope/app/interpreter/configure.zcml
src/zope/app/interpreter/interfaces.py
src/zope/app/interpreter/interpreter-configure.zcml
src/zope/app/interpreter/python.py
src/zope/app/interpreter/tests/__init__.py
src/zope/app/interpreter/tests/test_pythoninterpreter.py
